extensions/ublock-origin.crx
persine/__init__.py
persine/bridges/__init__.py
persine/bridges/amazon.py
persine/bridges/bridge.py
persine/bridges/youtube.py
persine/persona.py
persine/persona_engine.py
persine/utils.py
persine-0.1.4.dist-info/LICENSE
persine-0.1.4.dist-info/WHEEL
persine-0.1.4.dist-info/METADATA
persine-0.1.4.dist-info/RECORD
