Metadata-Version: 2.1
Name: persine
Version: 0.1.4
Summary: Persine is an automated tool to study and reverse-engineer algorithmic recommendation systems. It has a simple interface and encourages reproducible results.
Home-page: https://github.com/jsoma/persine
License: MIT
Keywords: algorithmic accountability,recommendation systems,scraping
Author: Jonathan Soma
Author-email: jonathan.soma@gmail.com
Requires-Python: >=3.6.3
Classifier: License :: OSI Approved :: MIT License
Classifier: Programming Language :: Python :: 3
Classifier: Programming Language :: Python :: 3.7
Classifier: Programming Language :: Python :: 3.8
Classifier: Programming Language :: Python :: 3.9
Provides-Extra: docs
Requires-Dist: Pillow (>=7.0.0)
Requires-Dist: beautifulsoup4 (>=4.6.3)
Requires-Dist: pandas (>=1.1.5,<2.0.0)
Requires-Dist: selenium (>=3.141.0,<4.0.0)
Requires-Dist: sphinx (>=3,<4); extra == "docs"
Project-URL: Documentation, https://persine.readthedocs.io
Project-URL: Repository, https://github.com/jsoma/persine
